pymovieinfo.py
setup.py
pymovieinfo.egg-info/PKG-INFO
pymovieinfo.egg-info/SOURCES.txt
pymovieinfo.egg-info/dependency_links.txt
pymovieinfo.egg-info/entry_points.txt
pymovieinfo.egg-info/pbr.json
pymovieinfo.egg-info/top_level.txt