Metadata-Version: 1.0
Name: pymovieinfo
Version: 0.2
Summary: Get information about any movie from the command line
Home-page: https://github.com/dhamaniasad/pymovieinfo
Author: Asad Dhamani
Author-email: dhamaniasad+code@gmail.com
License: Unlicense
Platform: UNKNOWN
